blockdiagcontrib/__init__.py
blockdiagcontrib/math.py
blockdiagcontrib_math-0.9.0.dist-info/DESCRIPTION.rst
blockdiagcontrib_math-0.9.0.dist-info/entry_points.txt
blockdiagcontrib_math-0.9.0.dist-info/METADATA
blockdiagcontrib_math-0.9.0.dist-info/metadata.json
blockdiagcontrib_math-0.9.0.dist-info/RECORD
blockdiagcontrib_math-0.9.0.dist-info/top_level.txt
blockdiagcontrib_math-0.9.0.dist-info/WHEEL
